{
  "frame_metadata": {
    "frame_id": 180,
    "timestamp": 1783668449.704984,
    "camera_resolution": [
      1280,
      720
    ]
  },
  "scene": {
    "floor_detected": false,
    "floor_normal": [
      0,
      1,
      0
    ],
    "camera_height": 0.0,
    "scene_summary": "person 1개, bowl 1개, bed 1개가 감지됨"
  },
  "objects": [
    {
      "id": 0,
      "label": "person",
      "yolo": {
        "confidence": 0.95,
        "bbox_2d": [
          172,
          1,
          1279,
          710
        ]
      },
      "sam": null,
      "depth": null,
      "spatial_3d": null,
      "affordance": null,
      "description": null
    },
    {
      "id": 1,
      "label": "bowl",
      "yolo": {
        "confidence": 0.34,
        "bbox_2d": [
          254,
          274,
          375,
          368
        ]
      },
      "sam": null,
      "depth": null,
      "spatial_3d": null,
      "affordance": null,
      "description": null
    },
    {
      "id": 2,
      "label": "bed",
      "yolo": {
        "confidence": 0.27,
        "bbox_2d": [
          0,
          283,
          246,
          711
        ]
      },
      "sam": null,
      "depth": null,
      "spatial_3d": null,
      "affordance": null,
      "description": null
    }
  ]
}